{"date":"2022-07-14T12:15:08.057Z","params":{"from":["EVN"],"to":["LED","MOW"],"labels":{"LED":"SPb, Pulkovo","MOW":"Moscow (all)","EVN":"Yerevan, Zvartnots"},"dateRange":{"days":30,"since":"2022-07-14T12:15:00.916Z"},"currency":"eur","request":{"chank":25,"delay":3000},"priceRange":{"lowPrice":75,"step":50},"output":"./ui/data/arm-rus-latest.json"},"stats":{"minPrice":114,"maxPrice":310,"minDuration":205,"maxDuration":2525,"maxTransfers":2,"failedRequests":0,"totalRequests":60},"results":[{"route":"EVN-MOW","origin":"EVN","destination":"MOW","price":114,"departure_at":"2022-07-15T22:50:00+04:00","transfers":0,"duration":205,"durationH":3,"link":"/search/EVN1507MOW1?t=YC16579110001657923300000205EVNDME_c641fb21bb8230ac48c52c6482a6e185_6680&search_date=14072022&expected_price_uuid=f3ff6dc6-48f6-42bf-8805-1f5c2271a16c&expected_price_currency=rub&marker=366337"},{"route":"EVN-MOW","origin":"EVN","destination":"MOW","price":131,"departure_at":"2022-07-17T01:25:00+04:00","transfers":0,"duration":225,"durationH":4,"link":"/search/EVN1707MOW2?t=UT16580067001658020200000225EVNVKO_8028ffa3ae184fef257796794f02be20_15306&search_date=14072022&expected_price_uuid=10712242-d4c2-4377-a30b-ffe9b8602769&expected_price_currency=rub&marker=366337"},{"route":"EVN-MOW","origin":"EVN","destination":"MOW","price":141,"departure_at":"2022-07-16T01:25:00+04:00","transfers":0,"duration":225,"durationH":4,"link":"/search/EVN1607MOW1?t=UT16579203001657933800000225EVNVKO_df5da431bc51393c500a9f7711c55e81_8243&search_date=14072022&expected_price_uuid=a5e0df85-3873-4525-936b-4b265f1e50e4&expected_price_currency=rub&marker=366337"},{"route":"EVN-MOW","origin":"EVN","destination":"MOW","price":146,"departure_at":"2022-07-19T00:15:00+04:00","transfers":1,"duration":1445,"durationH":24,"link":"/search/EVN1907MOW1?t=N416581753001658262000001445EVNAERSVO_7ab5048429993d3c36276bddf72664ad_8494&search_date=14072022&expected_price_uuid=a66c5037-28aa-4293-b501-f555d52afdf2&expected_price_currency=rub&marker=366337"},{"route":"EVN-MOW","origin":"EVN","destination":"MOW","price":161,"departure_at":"2022-07-27T23:30:00+04:00","transfers":0,"duration":225,"durationH":4,"link":"/search/EVN2707MOW1?t=UT16589502001658963700000225EVNVKO_ded8a75b8d4d4f03981f763181635a01_9423&search_date=14072022&expected_price_uuid=b9efba6d-da04-4575-b6e7-00c478263abb&expected_price_currency=rub&marker=366337"},{"route":"EVN-MOW","origin":"EVN","destination":"MOW","price":161,"departure_at":"2022-07-25T01:25:00+04:00","transfers":0,"duration":225,"durationH":4,"link":"/search/EVN2507MOW1?t=UT16586979001658711400000225EVNVKO_1cd3d83a7e13766d1f3601b9e9bbcf0d_9423&search_date=14072022&expected_price_uuid=e4053ce3-031e-4ba8-8d4d-6ae0d4911716&expected_price_currency=rub&marker=366337"},{"route":"EVN-MOW","origin":"EVN","destination":"MOW","price":161,"departure_at":"2022-07-24T23:30:00+04:00","transfers":0,"duration":225,"durationH":4,"link":"/search/EVN2407MOW1?t=UT16586910001658704500000225EVNVKO_65bc852e75a71985c38afc769c130616_9423&search_date=14072022&expected_price_uuid=11544cf7-5007-4a21-8dbd-39bcba05ba6c&expected_price_currency=rub&marker=366337"},{"route":"EVN-MOW","origin":"EVN","destination":"MOW","price":161,"departure_at":"2022-07-23T01:25:00+04:00","transfers":0,"duration":225,"durationH":4,"link":"/search/EVN2307MOW1?t=UT16585251001658538600000225EVNVKO_8d77afcf59cc0d73c0367441ce3977a9_9423&search_date=14072022&expected_price_uuid=d4fddbbe-b31a-4335-9da4-eda058ce970e&expected_price_currency=rub&marker=366337"},{"route":"EVN-MOW","origin":"EVN","destination":"MOW","price":161,"departure_at":"2022-07-22T01:25:00+04:00","transfers":0,"duration":225,"durationH":4,"link":"/search/EVN2207MOW1?t=UT16584387001658452200000225EVNVKO_d5ae32f76f56c9ec606c2a3958d4bf2b_9423&search_date=14072022&expected_price_uuid=b73fbfbd-8f0f-487d-b3d9-fcdc94cd0f91&expected_price_currency=rub&marker=366337"},{"route":"EVN-MOW","origin":"EVN","destination":"MOW","price":161,"departure_at":"2022-07-21T01:25:00+04:00","transfers":0,"duration":225,"durationH":4,"link":"/search/EVN2107MOW1?t=UT16583523001658365800000225EVNVKO_fca84eae98ed66a293696a03c3f24c13_9423&search_date=14072022&expected_price_uuid=29c65de0-a40e-4fbe-95a7-5c750ac3ea64&expected_price_currency=rub&marker=366337"},{"route":"EVN-MOW","origin":"EVN","destination":"MOW","price":161,"departure_at":"2022-07-20T23:30:00+04:00","transfers":0,"duration":225,"durationH":4,"link":"/search/EVN2007MOW1?t=UT16583454001658358900000225EVNVKO_b9c61748cabd79b6f1b68db5c3ce16b2_9423&search_date=14072022&expected_price_uuid=6817c2fd-f84c-42b9-b21f-284cac18bd86&expected_price_currency=rub&marker=366337"},{"route":"EVN-MOW","origin":"EVN","destination":"MOW","price":158,"departure_at":"2022-07-18T01:25:00+04:00","transfers":0,"duration":225,"durationH":4,"link":"/search/EVN1807MOW3?t=UT16580931001658106600000225EVNVKO_25c6a93c4353a8ec7cc327ef0deb6777_27650&search_date=14072022&expected_price_uuid=debb63b3-8548-4b3e-9add-e2100daa6538&expected_price_currency=rub&marker=366337"},{"route":"EVN-LED","origin":"EVN","destination":"LED","price":166,"departure_at":"2022-07-19T02:45:00+04:00","transfers":1,"duration":1285,"durationH":21,"link":"/search/EVN1907LED1?t=DP16581843001658261400001285EVNMRVLED_1b7c9a692200bd7886d6a0b6103b33df_9710&search_date=14072022&expected_price_uuid=b457ded3-626e-479a-9a7b-5ce4aedd0133&expected_price_currency=rub&marker=366337"},{"route":"EVN-LED","origin":"EVN","destination":"LED","price":181,"departure_at":"2022-07-20T01:25:00+04:00","transfers":1,"duration":1170,"durationH":20,"link":"/search/EVN2007LED1?t=UT16582659001658336100001170EVNVKOLED_71af183fdf3c67e204fca9b2e0e951ea_10553&search_date=14072022&expected_price_uuid=b90b0bcd-3669-4925-885e-7a89e828dfc8&expected_price_currency=rub&marker=366337"},{"route":"EVN-LED","origin":"EVN","destination":"LED","price":184,"departure_at":"2022-07-18T01:25:00+04:00","transfers":1,"duration":1180,"durationH":20,"link":"/search/EVN1807LED1?t=UT16580931001658163900001180EVNVKOLED_636063e821faafec61c91e510a215b28_10733&search_date=14072022&expected_price_uuid=d5641783-e1fd-4bca-a0fa-52af0ccc9431&expected_price_currency=rub&marker=366337"},{"route":"EVN-LED","origin":"EVN","destination":"LED","price":177,"departure_at":"2022-07-17T23:30:00+04:00","transfers":1,"duration":1295,"durationH":22,"link":"/search/EVN1707LED1?t=UT16580862001658163900001295EVNVKOLED_f977f1010517040b63459ca1715967a0_10318&search_date=14072022&expected_price_uuid=ebb11393-f30f-4de0-98f4-7b8e2421e59e&expected_price_currency=rub&marker=366337"},{"route":"EVN-LED","origin":"EVN","destination":"LED","price":176,"departure_at":"2022-07-15T22:50:00+04:00","transfers":1,"duration":1630,"durationH":27,"link":"/search/EVN1507LED1?t=YC16579110001658008800001630EVNDMELED_fc6bac2216093ac3f79a9ed0bbe4c4c0_10265&search_date=14072022&expected_price_uuid=f41b146a-4137-46a3-8a6a-10c955647cc1&expected_price_currency=rub&marker=366337"},{"route":"EVN-MOW","origin":"EVN","destination":"MOW","price":192,"departure_at":"2022-07-28T23:30:00+04:00","transfers":0,"duration":225,"durationH":4,"link":"/search/EVN2807MOW1?t=UT16590366001659050100000225EVNVKO_7fb9d78921117f5a699b0e784241af2d_11193&search_date=14072022&expected_price_uuid=46ed3e85-5491-4120-a19a-96e1af8dbf70&expected_price_currency=rub&marker=366337"},{"route":"EVN-MOW","origin":"EVN","destination":"MOW","price":189,"departure_at":"2022-07-26T18:45:00+04:00","transfers":1,"duration":430,"durationH":7,"link":"/search/EVN2607MOW1?t=SU16588467001658872500000430EVNMRVSVO_d8d1e616341ed95edf4187b025ac5b73_11032&search_date=14072022&expected_price_uuid=4d393b2c-afc7-44f9-82b8-333e257187da&expected_price_currency=rub&marker=366337"},{"route":"EVN-LED","origin":"EVN","destination":"LED","price":189,"departure_at":"2022-07-25T01:25:00+04:00","transfers":1,"duration":1150,"durationH":19,"link":"/search/EVN2507LED1?t=UT16586979001658766900001150EVNVKOLED_7b1c2bccecb6f48cb5b5b964bfc7ca9c_11028&search_date=14072022&expected_price_uuid=17c7e8fd-663b-4eb6-a83f-054c805f222e&expected_price_currency=rub&marker=366337"},{"route":"EVN-LED","origin":"EVN","destination":"LED","price":189,"departure_at":"2022-07-23T01:25:00+04:00","transfers":1,"duration":1185,"durationH":20,"link":"/search/EVN2307LED1?t=UT16585251001658596200001185EVNVKOLED_0dec31dbdededd2db2e55047a996bc33_11028&search_date=14072022&expected_price_uuid=4fd17e69-cabc-4d9b-b31e-61b099dc2c57&expected_price_currency=rub&marker=366337"},{"route":"EVN-LED","origin":"EVN","destination":"LED","price":189,"departure_at":"2022-07-24T23:30:00+04:00","transfers":1,"duration":1265,"durationH":21,"link":"/search/EVN2407LED1?t=UT16586910001658766900001265EVNVKOLED_c71f325b4dc4d1f731e054922d2769b4_11028&search_date=14072022&expected_price_uuid=ca7c9cbd-95db-4efe-86bc-c33789112ee8&expected_price_currency=rub&marker=366337"},{"route":"EVN-LED","origin":"EVN","destination":"LED","price":189,"departure_at":"2022-07-27T23:30:00+04:00","transfers":1,"duration":1295,"durationH":22,"link":"/search/EVN2707LED1?t=UT16589502001659027900001295EVNVKOLED_35ae293bbeee126015181a855767593b_11028&search_date=14072022&expected_price_uuid=ae3b7e78-7fa5-4625-b56a-dab907607c76&expected_price_currency=rub&marker=366337"},{"route":"EVN-LED","origin":"EVN","destination":"LED","price":189,"departure_at":"2022-07-22T18:40:00+04:00","transfers":1,"duration":1590,"durationH":27,"link":"/search/EVN2207LED1?t=UT16585008001658596200001590EVNVKOLED_ae9d9098fb9cd05f985e7ad12fe326bb_11028&search_date=14072022&expected_price_uuid=9192dd58-bd0c-4cc9-b3c9-3709bae6036f&expected_price_currency=rub&marker=366337"},{"route":"EVN-MOW","origin":"EVN","destination":"MOW","price":212,"departure_at":"2022-07-30T01:25:00+04:00","transfers":0,"duration":225,"durationH":4,"link":"/search/EVN3007MOW1?t=UT16591299001659143400000225EVNVKO_c1a20292edad339094515cb9afec2689_12373&search_date=14072022&expected_price_uuid=17c3c014-ce63-4fa7-8e97-454cd129016b&expected_price_currency=rub&marker=366337"},{"route":"EVN-MOW","origin":"EVN","destination":"MOW","price":212,"departure_at":"2022-07-29T01:25:00+04:00","transfers":0,"duration":225,"durationH":4,"link":"/search/EVN2907MOW1?t=UT16590435001659057000000225EVNVKO_dfc6117a9e8f2e989da91dd68bfe5934_12373&search_date=14072022&expected_price_uuid=ddd98cf2-e118-42b9-bd66-33aefc978a0a&expected_price_currency=rub&marker=366337"},{"route":"EVN-LED","origin":"EVN","destination":"LED","price":204,"departure_at":"2022-07-21T01:25:00+04:00","transfers":1,"duration":1180,"durationH":20,"link":"/search/EVN2107LED1?t=UT16583523001658423100001180EVNVKOLED_b6dab195184795ee505809d567ff4a41_11913&search_date=14072022&expected_price_uuid=e61c428a-8b8f-4fc1-bd8a-e1538122084c&expected_price_currency=rub&marker=366337"},{"route":"EVN-LED","origin":"EVN","destination":"LED","price":203,"departure_at":"2022-07-16T01:25:00+04:00","transfers":1,"duration":1475,"durationH":25,"link":"/search/EVN1607LED1?t=UT16579203001658008800001475EVNVKODMELED_9ce4c0490c990b6d4b258e3341ba9225_11843&search_date=14072022&expected_price_uuid=78bbfc83-9abc-4a6a-ba4d-6dbde77a428d&expected_price_currency=rub&marker=366337"},{"route":"EVN-LED","origin":"EVN","destination":"LED","price":219,"departure_at":"2022-07-28T01:25:00+04:00","transfers":1,"duration":1180,"durationH":20,"link":"/search/EVN2807LED1?t=UT16589571001659027900001180EVNVKOLED_09d1db8ccca9ba1c3ebfa8233b7b7358_12798&search_date=14072022&expected_price_uuid=14d963e4-694a-4afb-931b-6bfe9154e229&expected_price_currency=rub&marker=366337"},{"route":"EVN-LED","origin":"EVN","destination":"LED","price":219,"departure_at":"2022-07-26T02:45:00+04:00","transfers":1,"duration":1420,"durationH":24,"link":"/search/EVN2607LED1?t=5N16587891001658874300001420EVNMRVLED_abfceef6faf9ec76de22893091cbead8_12776&search_date=14072022&expected_price_uuid=360031ea-04bb-4090-bc19-26a285d54575&expected_price_currency=rub&marker=366337"},{"route":"EVN-MOW","origin":"EVN","destination":"MOW","price":236,"departure_at":"2022-08-01T23:50:00+04:00","transfers":1,"duration":1145,"durationH":19,"link":"/search/EVN0108MOW1?t=UT16593834001659452100001145EVNMRVVKO_7fdde7019b3652da1eb5081290ea57a2_13770&search_date=14072022&expected_price_uuid=effcc71c-0459-4631-aa3d-586c3a8cf650&expected_price_currency=rub&marker=366337"},{"route":"EVN-MOW","origin":"EVN","destination":"MOW","price":248,"departure_at":"2022-08-03T12:40:00+04:00","transfers":0,"duration":235,"durationH":4,"link":"/search/EVN0308MOW1?t=WZ16595160001659530100000235EVNDME_e76a2040bffedd39450706c83462bdf9_14500&search_date=14072022&expected_price_uuid=2d199c88-8f3b-4330-b2f7-072012491fe7&expected_price_currency=rub&marker=366337"},{"route":"EVN-MOW","origin":"EVN","destination":"MOW","price":236,"departure_at":"2022-08-09T07:50:00+04:00","transfers":1,"duration":665,"durationH":11,"link":"/search/EVN0908MOW1?t=UT16600170001660056900000665EVNMRVVKO_f2caf150706d878ba82a853f482f5a86_13769&search_date=14072022&expected_price_uuid=e4b9849c-ac63-4708-a8f8-86c961553d40&expected_price_currency=rub&marker=366337"},{"route":"EVN-MOW","origin":"EVN","destination":"MOW","price":236,"departure_at":"2022-08-08T23:50:00+04:00","transfers":1,"duration":1145,"durationH":19,"link":"/search/EVN0808MOW1?t=UT16599882001660056900001145EVNMRVVKO_fe558aab1994e5432e14dd3a8c8da2f6_13784&search_date=14072022&expected_price_uuid=08e74afc-f705-496c-b83d-6c30df82b8c8&expected_price_currency=rub&marker=366337"},{"route":"EVN-LED","origin":"EVN","destination":"LED","price":239,"departure_at":"2022-07-30T01:25:00+04:00","transfers":1,"duration":1185,"durationH":20,"link":"/search/EVN3007LED1?t=UT16591299001659201000001185EVNVKOLED_d095b4285d94b387a0036e41c9b7a940_13978&search_date=14072022&expected_price_uuid=028fd3f0-624c-4e3c-b37e-cecbb2e54bcf&expected_price_currency=rub&marker=366337"},{"route":"EVN-MOW","origin":"EVN","destination":"MOW","price":246,"departure_at":"2022-08-04T22:25:00+04:00","transfers":1,"duration":1485,"durationH":25,"link":"/search/EVN0408MOW1?t=SU16596375001659726600001485EVNVOGSVO_035892111c1a2608ff39f8fb572439bc_14371&search_date=14072022&expected_price_uuid=d67ef412-b9d0-49f5-8213-cddcbea1af6c&expected_price_currency=rub&marker=366337"},{"route":"EVN-LED","origin":"EVN","destination":"LED","price":239,"departure_at":"2022-07-29T18:40:00+04:00","transfers":1,"duration":1590,"durationH":27,"link":"/search/EVN2907LED1?t=UT16591056001659201000001590EVNVKOLED_71e41af6b5aa7f0329306b8b12ac4407_13978&search_date=14072022&expected_price_uuid=9e4908da-3ef2-4549-bfe7-c31d4969fcbd&expected_price_currency=rub&marker=366337"},{"route":"EVN-MOW","origin":"EVN","destination":"MOW","price":261,"departure_at":"2022-07-31T23:30:00+04:00","transfers":0,"duration":205,"durationH":3,"link":"/search/EVN3107MOW1?t=3F16592958001659308100000205EVNVKO_ae3d840d535dbd473e08d7fbddffade0_15214&search_date=14072022&expected_price_uuid=ade03e3f-95cd-4091-879e-529ccabdd58b&expected_price_currency=rub&marker=366337"},{"route":"EVN-MOW","origin":"EVN","destination":"MOW","price":248,"departure_at":"2022-08-02T12:40:00+04:00","transfers":0,"duration":235,"durationH":4,"link":"/search/EVN0208MOW1?t=WZ16594296001659443700000235EVNDME_89ed5453a1df0d53f3cb72aec146627d_14450&search_date=14072022&expected_price_uuid=8adbaf73-9258-402a-b2ec-ae79370b8826&expected_price_currency=rub&marker=366337"},{"route":"EVN-MOW","origin":"EVN","destination":"MOW","price":246,"departure_at":"2022-08-06T22:25:00+04:00","transfers":1,"duration":2485,"durationH":41,"link":"/search/EVN0608MOW1?t=SU16598103001659959400002485EVNVOGSVO_2201905be21ce7139b6c1ed6e71a49bf_14371&search_date=14072022&expected_price_uuid=47de86c5-766a-48c1-b613-951ae91e1755&expected_price_currency=rub&marker=366337"},{"route":"EVN-MOW","origin":"EVN","destination":"MOW","price":262,"departure_at":"2022-08-11T13:00:00+04:00","transfers":0,"duration":220,"durationH":4,"link":"/search/EVN1108MOW2?t=5F16602084001660221600000220EVNDME_0c3dea4d5bf05f05541b46b850153e12_30562&search_date=14072022&expected_price_uuid=3ed7f36b-7de2-4487-8588-addfbb295af4&expected_price_currency=rub&marker=366337"},{"route":"EVN-MOW","origin":"EVN","destination":"MOW","price":261,"departure_at":"2022-08-05T09:00:00+04:00","transfers":0,"duration":220,"durationH":4,"link":"/search/EVN0508MOW1?t=3F16596756001659688800000220EVNVKO_b6ef17e66bdf4afdc8fbbed37e865a88_15214&search_date=14072022&expected_price_uuid=db2ee6da-4b90-4586-9f78-9b484330915c&expected_price_currency=rub&marker=366337"},{"route":"EVN-MOW","origin":"EVN","destination":"MOW","price":281,"departure_at":"2022-08-12T21:30:00+04:00","transfers":0,"duration":220,"durationH":4,"link":"/search/EVN1208MOW1?t=3F16603254001660338600000220EVNVKO_53586486c239e96f244b1eb279d4d71f_16402&search_date=14072022&expected_price_uuid=2d7847da-10e9-405f-b564-27b8274b012e&expected_price_currency=rub&marker=366337"},{"route":"EVN-LED","origin":"EVN","destination":"LED","price":274,"departure_at":"2022-08-13T22:25:00+04:00","transfers":2,"duration":660,"durationH":11,"link":"/search/EVN1308LED1?t=SU16604151001660454700000660EVNVOGSVOLED_3106968bb6e893e81541fbe739b6a6ee_15985&search_date=14072022&expected_price_uuid=0693cf6d-5789-4115-a351-d9477de28643&expected_price_currency=rub&marker=366337"},{"route":"EVN-LED","origin":"EVN","destination":"LED","price":274,"departure_at":"2022-08-06T22:25:00+04:00","transfers":2,"duration":715,"durationH":12,"link":"/search/EVN0608LED1?t=SU16598103001659853200000715EVNVOGSVOLED_3445249b97fe9e9cf13664e0dd668add_15968&search_date=14072022&expected_price_uuid=05741a1b-9224-431d-8875-fa41721f1b2b&expected_price_currency=rub&marker=366337"},{"route":"EVN-MOW","origin":"EVN","destination":"MOW","price":274,"departure_at":"2022-08-10T11:25:00+04:00","transfers":1,"duration":870,"durationH":15,"link":"/search/EVN1008MOW1?t=SU16601163001660168500000870EVNMRVSVO_b0d8347feb066360669357e07bad3eb8_16012&search_date=14072022&expected_price_uuid=7319b00f-898b-4c57-880f-d59a024cd027&expected_price_currency=rub&marker=366337"},{"route":"EVN-LED","origin":"EVN","destination":"LED","price":266,"departure_at":"2022-08-09T23:55:00+04:00","transfers":1,"duration":960,"durationH":16,"link":"/search/EVN0908LED1?t=A416600749001660132500000960EVNMRVLED_9f5b00b5b184fcb3931d4821ace8f9b8_15550&search_date=14072022&expected_price_uuid=3bc1b38f-faaf-4b80-bf6b-1b057aaa1ef2&expected_price_currency=rub&marker=366337"},{"route":"EVN-LED","origin":"EVN","destination":"LED","price":269,"departure_at":"2022-08-04T22:25:00+04:00","transfers":1,"duration":1210,"durationH":20,"link":"/search/EVN0408LED1?t=SU16596375001659710100001210EVNVOGLED_9512ff2730dc7e739ba0a7c154b3a10d_15707&search_date=14072022&expected_price_uuid=ee28e44d-616e-47df-a435-9b58a6ad8d6e&expected_price_currency=rub&marker=366337"},{"route":"EVN-LED","origin":"EVN","destination":"LED","price":267,"departure_at":"2022-08-02T02:45:00+04:00","transfers":1,"duration":1420,"durationH":24,"link":"/search/EVN0208LED1?t=5N16593939001659479100001420EVNMRVLED_445487d298e621983c999e5af505fde3_15562&search_date=14072022&expected_price_uuid=ca902c34-324a-4eaa-aff8-172cff6c3fde&expected_price_currency=rub&marker=366337"},{"route":"EVN-LED","origin":"EVN","destination":"LED","price":257,"departure_at":"2022-08-01T23:50:00+04:00","transfers":1,"duration":1595,"durationH":27,"link":"/search/EVN0108LED2?t=5N16593834001659479100001595EVNMRVLED_0dbd67ba9988e746dced9d1f05f74342_29956&search_date=14072022&expected_price_uuid=c3773789-de7e-4a3c-9e10-134e333f8470&expected_price_currency=rub&marker=366337"},{"route":"EVN-MOW","origin":"EVN","destination":"MOW","price":281,"departure_at":"2022-08-07T09:00:00+04:00","transfers":0,"duration":220,"durationH":4,"link":"/search/EVN0708MOW2?t=3F16598484001659861600000220EVNVKO_d8449b3c11b41b1e5012a185bb6bc75d_32804&search_date=14072022&expected_price_uuid=216b3e4b-276f-45b9-85d9-dd5f8e2435fc&expected_price_currency=rub&marker=366337"},{"route":"EVN-LED","origin":"EVN","destination":"LED","price":276,"departure_at":"2022-08-08T23:50:00+04:00","transfers":2,"duration":1285,"durationH":21,"link":"/search/EVN0808LED1?t=SU16599882001660065300001285EVNMRVSVOLED_40acc743e50598a8bc8817e90cccfb29_16127&search_date=14072022&expected_price_uuid=5abfa912-a763-4f5d-acfc-6fe6912d654e&expected_price_currency=rub&marker=366337"},{"route":"EVN-MOW","origin":"EVN","destination":"MOW","price":272,"departure_at":"2022-08-13T22:25:00+04:00","transfers":1,"duration":2285,"durationH":38,"link":"/search/EVN1308MOW1?t=SU16604151001660552200002285EVNVOGVKO_bf841422a08d76815edac86d687469ce_15849&search_date=14072022&expected_price_uuid=082e4d83-fb4f-40f4-a1fc-40148eb6e3a1&expected_price_currency=rub&marker=366337"},{"route":"EVN-LED","origin":"EVN","destination":"LED","price":301,"departure_at":"2022-08-12T06:50:00+04:00","transfers":0,"duration":280,"durationH":5,"link":"/search/EVN1208LED1?t=3F16602726001660289400000280EVNLED_ca6681ebe744ab838573b03109d610ee_17591&search_date=14072022&expected_price_uuid=c16d809b-d25d-44e6-a4da-e94eaef30275&expected_price_currency=rub&marker=366337"},{"route":"EVN-LED","origin":"EVN","destination":"LED","price":301,"departure_at":"2022-08-10T22:00:00+04:00","transfers":0,"duration":280,"durationH":5,"link":"/search/EVN1008LED1?t=3F16601544001660171200000280EVNLED_a4273c7df4d78e676d27dbd0fe0635fe_17591&search_date=14072022&expected_price_uuid=d26ee53f-155e-415f-9712-fc47aecb2982&expected_price_currency=rub&marker=366337"},{"route":"EVN-LED","origin":"EVN","destination":"LED","price":301,"departure_at":"2022-08-05T06:50:00+04:00","transfers":0,"duration":280,"durationH":5,"link":"/search/EVN0508LED1?t=3F16596678001659684600000280EVNLED_07d1c2b44ec8a1159639e86bdd15d2e5_17591&search_date=14072022&expected_price_uuid=8560d6f4-7de4-438f-9d05-5c459ed64bc8&expected_price_currency=rub&marker=366337"},{"route":"EVN-LED","origin":"EVN","destination":"LED","price":300,"departure_at":"2022-07-31T01:25:00+04:00","transfers":1,"duration":1150,"durationH":19,"link":"/search/EVN3107LED1?t=UT16592163001659285300001150EVNVKOLED_9cb180a6b689d50cdf20e41fbb2257de_17518&search_date=14072022&expected_price_uuid=ea206faf-653d-406d-9740-df0b1441dc3b&expected_price_currency=rub&marker=366337"},{"route":"EVN-LED","origin":"EVN","destination":"LED","price":304,"departure_at":"2022-08-11T22:25:00+04:00","transfers":1,"duration":1210,"durationH":20,"link":"/search/EVN1108LED1?t=SU16602423001660314900001210EVNVOGLED_4599a6cdae04bbcec4b4ddf303bdacf5_17757&search_date=14072022&expected_price_uuid=5dc6e232-f7ec-4f16-aa7f-02ef438e23ff&expected_price_currency=rub&marker=366337"},{"route":"EVN-LED","origin":"EVN","destination":"LED","price":310,"departure_at":"2022-08-03T22:20:00+04:00","transfers":1,"duration":1685,"durationH":28,"link":"/search/EVN0308LED1?t=5N16595508001659651900001685EVNMRVLED_c7ef5d0e8a99f89d4a767c066520b3bd_18119&search_date=14072022&expected_price_uuid=a9facf87-4b6c-440d-8b17-bc28e6658599&expected_price_currency=rub&marker=366337"},{"route":"EVN-LED","origin":"EVN","destination":"LED","price":297,"departure_at":"2022-08-07T07:30:00+04:00","transfers":1,"duration":2525,"durationH":42,"link":"/search/EVN0708LED1?t=5N16598430001659994500002525EVNMRVLED_99f8c531829494fd2b80e06b32d20f85_17350&search_date=14072022&expected_price_uuid=ad51909d-1a86-4b0e-9d66-59b66a29f924&expected_price_currency=rub&marker=366337"}]}